<annotation>
  <folder>folder_name</folder>
  <filename>00958333333333-90_78-151&amp;527_343&amp;594-349&amp;590_169&amp;587_152&amp;523_332&amp;526-0_0_12_33_25_31_18-47-31-01.jpg.jpg</filename>
  <source>
    <database>Unknown</database>
  </source>
  <size>
    <width>720</width>
    <height>1160</height>
    <channel>3</channel>
  </size>
  <segmented>0</segmented>
  <object>
    <name>blue</name>
    <pose>Unspecified</pose>
    <truncated>0</truncated>
    <difficult>0</difficult>
    <bndbox>
      <xmin>151</xmin>
      <ymin>527</ymin>
      <xmax>343</xmax>
      <ymax>594</ymax>
    </bndbox>
  </object>
</annotation>
