<annotation>
  <folder>folder_name</folder>
  <filename>00955459770115-95_81-282&amp;469_434&amp;537-436&amp;547_278&amp;529_277&amp;471_435&amp;489-0_0_32_31_31_3_27-87-16-01.jpg.jpg</filename>
  <source>
    <database>Unknown</database>
  </source>
  <size>
    <width>720</width>
    <height>1160</height>
    <channel>3</channel>
  </size>
  <segmented>0</segmented>
  <object>
    <name>blue</name>
    <pose>Unspecified</pose>
    <truncated>0</truncated>
    <difficult>0</difficult>
    <bndbox>
      <xmin>282</xmin>
      <ymin>469</ymin>
      <xmax>434</xmax>
      <ymax>537</ymax>
    </bndbox>
  </object>
</annotation>
