<annotation>
  <folder>folder_name</folder>
  <filename>00969827586207-89_92-339&amp;467_521&amp;534-521&amp;528_344&amp;537_341&amp;477_518&amp;468-0_0_31_31_23_29_28-156-39-01.jpg.jpg</filename>
  <source>
    <database>Unknown</database>
  </source>
  <size>
    <width>720</width>
    <height>1160</height>
    <channel>3</channel>
  </size>
  <segmented>0</segmented>
  <object>
    <name>blue</name>
    <pose>Unspecified</pose>
    <truncated>0</truncated>
    <difficult>0</difficult>
    <bndbox>
      <xmin>339</xmin>
      <ymin>467</ymin>
      <xmax>521</xmax>
      <ymax>534</ymax>
    </bndbox>
  </object>
</annotation>
