<annotation>
  <folder>folder_name</folder>
  <filename>00965517241379-90_88-220&amp;589_403&amp;653-409&amp;648_218&amp;653_218&amp;593_409&amp;588-0_0_33_13_32_31_29-120-24-01.jpg.jpg</filename>
  <source>
    <database>Unknown</database>
  </source>
  <size>
    <width>720</width>
    <height>1160</height>
    <channel>3</channel>
  </size>
  <segmented>0</segmented>
  <object>
    <name>blue</name>
    <pose>Unspecified</pose>
    <truncated>0</truncated>
    <difficult>0</difficult>
    <bndbox>
      <xmin>220</xmin>
      <ymin>589</ymin>
      <xmax>403</xmax>
      <ymax>653</ymax>
    </bndbox>
  </object>
</annotation>
