<annotation>
  <folder>folder_name</folder>
  <filename>00964798850574-90_85-256&amp;489_433&amp;559-433&amp;561_251&amp;553_255&amp;490_437&amp;498-0_0_20_25_24_27_11-169-14-01.jpg.jpg</filename>
  <source>
    <database>Unknown</database>
  </source>
  <size>
    <width>720</width>
    <height>1160</height>
    <channel>3</channel>
  </size>
  <segmented>0</segmented>
  <object>
    <name>blue</name>
    <pose>Unspecified</pose>
    <truncated>0</truncated>
    <difficult>0</difficult>
    <bndbox>
      <xmin>256</xmin>
      <ymin>489</ymin>
      <xmax>433</xmax>
      <ymax>559</ymax>
    </bndbox>
  </object>
</annotation>
