<annotation>
  <folder>folder_name</folder>
  <filename>00974616858238-90_91-267&amp;611_440&amp;686-449&amp;682_269&amp;686_270&amp;614_450&amp;610-0_0_24_22_28_29_33-181-17-01.jpg.jpg</filename>
  <source>
    <database>Unknown</database>
  </source>
  <size>
    <width>720</width>
    <height>1160</height>
    <channel>3</channel>
  </size>
  <segmented>0</segmented>
  <object>
    <name>blue</name>
    <pose>Unspecified</pose>
    <truncated>0</truncated>
    <difficult>0</difficult>
    <bndbox>
      <xmin>267</xmin>
      <ymin>611</ymin>
      <xmax>440</xmax>
      <ymax>686</ymax>
    </bndbox>
  </object>
</annotation>
