<annotation>
  <folder>folder_name</folder>
  <filename>00977011494253-90_86-209&amp;504_406&amp;568-412&amp;575_206&amp;566_201&amp;497_407&amp;506-0_12_1_24_24_26_26-124-18-01.jpg.jpg</filename>
  <source>
    <database>Unknown</database>
  </source>
  <size>
    <width>720</width>
    <height>1160</height>
    <channel>3</channel>
  </size>
  <segmented>0</segmented>
  <object>
    <name>blue</name>
    <pose>Unspecified</pose>
    <truncated>0</truncated>
    <difficult>0</difficult>
    <bndbox>
      <xmin>209</xmin>
      <ymin>504</ymin>
      <xmax>406</xmax>
      <ymax>568</ymax>
    </bndbox>
  </object>
</annotation>
