<annotation>
  <folder>folder_name</folder>
  <filename>00981800766283-90_88-181&amp;483_371&amp;541-381&amp;548_179&amp;548_181&amp;471_383&amp;471-0_0_9_24_26_31_19-175-22-01.jpg.jpg</filename>
  <source>
    <database>Unknown</database>
  </source>
  <size>
    <width>720</width>
    <height>1160</height>
    <channel>3</channel>
  </size>
  <segmented>0</segmented>
  <object>
    <name>blue</name>
    <pose>Unspecified</pose>
    <truncated>0</truncated>
    <difficult>0</difficult>
    <bndbox>
      <xmin>181</xmin>
      <ymin>483</ymin>
      <xmax>371</xmax>
      <ymax>541</ymax>
    </bndbox>
  </object>
</annotation>
