<annotation>
  <folder>folder_name</folder>
  <filename>00990421455938-91_87-230&amp;464_426&amp;526-428&amp;525_227&amp;517_221&amp;457_422&amp;465-0_0_4_30_31_31_0-95-11-01.jpg.jpg</filename>
  <source>
    <database>Unknown</database>
  </source>
  <size>
    <width>720</width>
    <height>1160</height>
    <channel>3</channel>
  </size>
  <segmented>0</segmented>
  <object>
    <name>blue</name>
    <pose>Unspecified</pose>
    <truncated>0</truncated>
    <difficult>0</difficult>
    <bndbox>
      <xmin>230</xmin>
      <ymin>464</ymin>
      <xmax>426</xmax>
      <ymax>526</ymax>
    </bndbox>
  </object>
</annotation>
