<annotation>
  <folder>folder_name</folder>
  <filename>014375-87_270-300&amp;423_507&amp;493-505&amp;482_302&amp;493_300&amp;437_507&amp;423-0_0_3_24_28_31_33_30-159-28-02.jpg.jpg</filename>
  <source>
    <database>Unknown</database>
  </source>
  <size>
    <width>720</width>
    <height>1160</height>
    <channel>3</channel>
  </size>
  <segmented>0</segmented>
  <object>
    <name>green</name>
    <pose>Unspecified</pose>
    <truncated>0</truncated>
    <difficult>0</difficult>
    <bndbox>
      <xmin>300</xmin>
      <ymin>423</ymin>
      <xmax>507</xmax>
      <ymax>493</ymax>
    </bndbox>
  </object>
</annotation>
