<annotation>
  <folder>folder_name</folder>
  <filename>00952586206897-92_94-308&amp;473_479&amp;534-471&amp;535_308&amp;523_311&amp;469_474&amp;481-0_0_33_26_28_8_29-114-28-01.jpg.jpg</filename>
  <source>
    <database>Unknown</database>
  </source>
  <size>
    <width>720</width>
    <height>1160</height>
    <channel>3</channel>
  </size>
  <segmented>0</segmented>
  <object>
    <name>blue</name>
    <pose>Unspecified</pose>
    <truncated>0</truncated>
    <difficult>0</difficult>
    <bndbox>
      <xmin>308</xmin>
      <ymin>473</ymin>
      <xmax>479</xmax>
      <ymax>534</ymax>
    </bndbox>
  </object>
</annotation>
