<annotation>
  <folder>folder_name</folder>
  <filename>00965038314176-92_85-375&amp;407_546&amp;473-554&amp;472_378&amp;463_375&amp;405_551&amp;414-0_0_25_15_33_32_33-102-8-01.jpg.jpg</filename>
  <source>
    <database>Unknown</database>
  </source>
  <size>
    <width>720</width>
    <height>1160</height>
    <channel>3</channel>
  </size>
  <segmented>0</segmented>
  <object>
    <name>blue</name>
    <pose>Unspecified</pose>
    <truncated>0</truncated>
    <difficult>0</difficult>
    <bndbox>
      <xmin>375</xmin>
      <ymin>407</ymin>
      <xmax>546</xmax>
      <ymax>473</ymax>
    </bndbox>
  </object>
</annotation>
