<annotation>
  <folder>folder_name</folder>
  <filename>00974616858238-89_91-303&amp;483_460&amp;547-458&amp;528_310&amp;546_307&amp;490_455&amp;472-0_9_33_11_26_29_32-128-36-01.jpg.jpg</filename>
  <source>
    <database>Unknown</database>
  </source>
  <size>
    <width>720</width>
    <height>1160</height>
    <channel>3</channel>
  </size>
  <segmented>0</segmented>
  <object>
    <name>blue</name>
    <pose>Unspecified</pose>
    <truncated>0</truncated>
    <difficult>0</difficult>
    <bndbox>
      <xmin>303</xmin>
      <ymin>483</ymin>
      <xmax>460</xmax>
      <ymax>547</ymax>
    </bndbox>
  </object>
</annotation>
