<annotation>
  <folder>folder_name</folder>
  <filename>00977011494253-90_87-284&amp;530_461&amp;600-464&amp;595_286&amp;598_286&amp;537_464&amp;534-0_0_25_33_8_29_25-105-15-01.jpg.jpg</filename>
  <source>
    <database>Unknown</database>
  </source>
  <size>
    <width>720</width>
    <height>1160</height>
    <channel>3</channel>
  </size>
  <segmented>0</segmented>
  <object>
    <name>blue</name>
    <pose>Unspecified</pose>
    <truncated>0</truncated>
    <difficult>0</difficult>
    <bndbox>
      <xmin>284</xmin>
      <ymin>530</ymin>
      <xmax>461</xmax>
      <ymax>600</ymax>
    </bndbox>
  </object>
</annotation>
