<annotation>
  <folder>folder_name</folder>
  <filename>00973539272031-91_86-202&amp;525_409&amp;588-395&amp;584_221&amp;574_213&amp;516_387&amp;526-0_9_9_10_29_31_33-76-8-01.jpg.jpg</filename>
  <source>
    <database>Unknown</database>
  </source>
  <size>
    <width>720</width>
    <height>1160</height>
    <channel>3</channel>
  </size>
  <segmented>0</segmented>
  <object>
    <name>blue</name>
    <pose>Unspecified</pose>
    <truncated>0</truncated>
    <difficult>0</difficult>
    <bndbox>
      <xmin>202</xmin>
      <ymin>525</ymin>
      <xmax>409</xmax>
      <ymax>588</ymax>
    </bndbox>
  </object>
</annotation>
