<annotation>
  <folder>folder_name</folder>
  <filename>00989224137931-97_79-400&amp;528_568&amp;598-561&amp;602_395&amp;582_400&amp;528_566&amp;548-0_0_26_18_32_33_29-116-34-01.jpg.jpg</filename>
  <source>
    <database>Unknown</database>
  </source>
  <size>
    <width>720</width>
    <height>1160</height>
    <channel>3</channel>
  </size>
  <segmented>0</segmented>
  <object>
    <name>blue</name>
    <pose>Unspecified</pose>
    <truncated>0</truncated>
    <difficult>0</difficult>
    <bndbox>
      <xmin>400</xmin>
      <ymin>528</ymin>
      <xmax>568</xmax>
      <ymax>598</ymax>
    </bndbox>
  </object>
</annotation>
