<annotation>
  <folder>folder_name</folder>
  <filename>00983596743295-91_90-312&amp;505_483&amp;565-484&amp;570_315&amp;557_320&amp;497_489&amp;510-0_0_33_2_28_24_32-138-28-01.jpg.jpg</filename>
  <source>
    <database>Unknown</database>
  </source>
  <size>
    <width>720</width>
    <height>1160</height>
    <channel>3</channel>
  </size>
  <segmented>0</segmented>
  <object>
    <name>blue</name>
    <pose>Unspecified</pose>
    <truncated>0</truncated>
    <difficult>0</difficult>
    <bndbox>
      <xmin>312</xmin>
      <ymin>505</ymin>
      <xmax>483</xmax>
      <ymax>565</ymax>
    </bndbox>
  </object>
</annotation>
