<annotation>
  <folder>folder_name</folder>
  <filename>010625-90_93-301&amp;363_490&amp;431-493&amp;431_301&amp;426_306&amp;362_498&amp;367-0_0_17_22_24_24_33-116-15.jpg.jpg</filename>
  <source>
    <database>Unknown</database>
  </source>
  <size>
    <width>720</width>
    <height>1160</height>
    <channel>3</channel>
  </size>
  <segmented>0</segmented>
  <object>
    <name>green</name>
    <pose>Unspecified</pose>
    <truncated>0</truncated>
    <difficult>0</difficult>
    <bndbox>
      <xmin>301</xmin>
      <ymin>363</ymin>
      <xmax>490</xmax>
      <ymax>431</ymax>
    </bndbox>
  </object>
</annotation>
