<annotation>
  <folder>folder_name</folder>
  <filename>01125-90_87-241&amp;439_432&amp;502-426&amp;504_247&amp;501_247&amp;436_426&amp;439-0_0_18_25_26_27_15-164-29.jpg.jpg</filename>
  <source>
    <database>Unknown</database>
  </source>
  <size>
    <width>720</width>
    <height>1160</height>
    <channel>3</channel>
  </size>
  <segmented>0</segmented>
  <object>
    <name>green</name>
    <pose>Unspecified</pose>
    <truncated>0</truncated>
    <difficult>0</difficult>
    <bndbox>
      <xmin>241</xmin>
      <ymin>439</ymin>
      <xmax>432</xmax>
      <ymax>502</ymax>
    </bndbox>
  </object>
</annotation>
