<annotation>
  <folder>folder_name</folder>
  <filename>01375-87_92-176&amp;302_361&amp;379-365&amp;371_189&amp;381_180&amp;318_356&amp;308-0_0_9_25_30_30_27-158-30.jpg.jpg</filename>
  <source>
    <database>Unknown</database>
  </source>
  <size>
    <width>720</width>
    <height>1160</height>
    <channel>3</channel>
  </size>
  <segmented>0</segmented>
  <object>
    <name>green</name>
    <pose>Unspecified</pose>
    <truncated>0</truncated>
    <difficult>0</difficult>
    <bndbox>
      <xmin>176</xmin>
      <ymin>302</ymin>
      <xmax>361</xmax>
      <ymax>379</ymax>
    </bndbox>
  </object>
</annotation>
