<annotation>
  <folder>folder_name</folder>
  <filename>0153125-89_95-185&amp;461_422&amp;543-436&amp;537_181&amp;554_181&amp;463_436&amp;446-0_0_26_23_26_28_30-119-25.jpg.jpg</filename>
  <source>
    <database>Unknown</database>
  </source>
  <size>
    <width>720</width>
    <height>1160</height>
    <channel>3</channel>
  </size>
  <segmented>0</segmented>
  <object>
    <name>green</name>
    <pose>Unspecified</pose>
    <truncated>0</truncated>
    <difficult>0</difficult>
    <bndbox>
      <xmin>185</xmin>
      <ymin>461</ymin>
      <xmax>422</xmax>
      <ymax>543</ymax>
    </bndbox>
  </object>
</annotation>
