<annotation>
  <folder>folder_name</folder>
  <filename>016875-90_84-208&amp;393_476&amp;474-463&amp;483_210&amp;481_210&amp;402_463&amp;404-0_0_4_17_31_30_33-74-28.jpg.jpg</filename>
  <source>
    <database>Unknown</database>
  </source>
  <size>
    <width>720</width>
    <height>1160</height>
    <channel>3</channel>
  </size>
  <segmented>0</segmented>
  <object>
    <name>green</name>
    <pose>Unspecified</pose>
    <truncated>0</truncated>
    <difficult>0</difficult>
    <bndbox>
      <xmin>208</xmin>
      <ymin>393</ymin>
      <xmax>476</xmax>
      <ymax>474</ymax>
    </bndbox>
  </object>
</annotation>
