<annotation>
  <folder>folder_name</folder>
  <filename>01953125-90_261-221&amp;500_471&amp;578-471&amp;578_230&amp;569_221&amp;500_467&amp;504-0_0_3_24_27_31_27_31-84-41.jpg.jpg</filename>
  <source>
    <database>Unknown</database>
  </source>
  <size>
    <width>720</width>
    <height>1160</height>
    <channel>3</channel>
  </size>
  <segmented>0</segmented>
  <object>
    <name>green</name>
    <pose>Unspecified</pose>
    <truncated>0</truncated>
    <difficult>0</difficult>
    <bndbox>
      <xmin>221</xmin>
      <ymin>500</ymin>
      <xmax>471</xmax>
      <ymax>578</ymax>
    </bndbox>
  </object>
</annotation>
