<annotation>
  <folder>folder_name</folder>
  <filename>0196875-83_91-350&amp;511_553&amp;614-564&amp;580_352&amp;626_349&amp;536_561&amp;490-0_0_7_30_16_25_33-148-13.jpg.jpg</filename>
  <source>
    <database>Unknown</database>
  </source>
  <size>
    <width>720</width>
    <height>1160</height>
    <channel>3</channel>
  </size>
  <segmented>0</segmented>
  <object>
    <name>green</name>
    <pose>Unspecified</pose>
    <truncated>0</truncated>
    <difficult>0</difficult>
    <bndbox>
      <xmin>350</xmin>
      <ymin>511</ymin>
      <xmax>553</xmax>
      <ymax>614</ymax>
    </bndbox>
  </object>
</annotation>
