<annotation>
  <folder>folder_name</folder>
  <filename>0196875-86_97-230&amp;296_450&amp;400-459&amp;372_246&amp;401_245&amp;315_458&amp;286-0_0_7_27_17_24_32-107-12.jpg.jpg</filename>
  <source>
    <database>Unknown</database>
  </source>
  <size>
    <width>720</width>
    <height>1160</height>
    <channel>3</channel>
  </size>
  <segmented>0</segmented>
  <object>
    <name>green</name>
    <pose>Unspecified</pose>
    <truncated>0</truncated>
    <difficult>0</difficult>
    <bndbox>
      <xmin>230</xmin>
      <ymin>296</ymin>
      <xmax>450</xmax>
      <ymax>400</ymax>
    </bndbox>
  </object>
</annotation>
