<annotation>
  <folder>folder_name</folder>
  <filename>0225-96_74-251&amp;510_468&amp;605-485&amp;617_253&amp;588_232&amp;509_464&amp;538-0_0_19_22_24_33_33-102-87.jpg.jpg</filename>
  <source>
    <database>Unknown</database>
  </source>
  <size>
    <width>720</width>
    <height>1160</height>
    <channel>3</channel>
  </size>
  <segmented>0</segmented>
  <object>
    <name>green</name>
    <pose>Unspecified</pose>
    <truncated>0</truncated>
    <difficult>0</difficult>
    <bndbox>
      <xmin>251</xmin>
      <ymin>510</ymin>
      <xmax>468</xmax>
      <ymax>605</ymax>
    </bndbox>
  </object>
</annotation>
