<annotation>
  <folder>folder_name</folder>
  <filename>0275-90_84-192&amp;463_523&amp;566-534&amp;562_200&amp;553_181&amp;461_515&amp;470-0_0_24_26_27_14_33-88-143.jpg.jpg</filename>
  <source>
    <database>Unknown</database>
  </source>
  <size>
    <width>720</width>
    <height>1160</height>
    <channel>3</channel>
  </size>
  <segmented>0</segmented>
  <object>
    <name>green</name>
    <pose>Unspecified</pose>
    <truncated>0</truncated>
    <difficult>0</difficult>
    <bndbox>
      <xmin>192</xmin>
      <ymin>463</ymin>
      <xmax>523</xmax>
      <ymax>566</ymax>
    </bndbox>
  </object>
</annotation>
